deezer/__init__.py
deezer/auth.py
deezer/client.py
deezer/dates.py
deezer/exceptions.py
deezer/pagination.py
deezer/utils.py
deezer/resources/__init__.py
deezer/resources/album.py
deezer/resources/artist.py
deezer/resources/chart.py
deezer/resources/editorial.py
deezer/resources/episode.py
deezer/resources/genre.py
deezer/resources/playlist.py
deezer/resources/podcast.py
deezer/resources/radio.py
deezer/resources/resource.py
deezer/resources/track.py
deezer/resources/user.py
deezer_python-7.2.0.dist-info/licenses/LICENSE.txt
deezer_python-7.2.0.dist-info/METADATA
deezer_python-7.2.0.dist-info/WHEEL
deezer_python-7.2.0.dist-info/top_level.txt
deezer_python-7.2.0.dist-info/RECORD
