Metadata-Version: 2.4
Name: deezer-python
Version: 7.2.0
Summary: A friendly wrapper library for the Deezer API
Author-email: Bruno Alla <alla.brunoo@gmail.com>
License-Expression: MIT
Project-URL: Bug Tracker, https://github.com/browniebroke/deezer-python/issues
Project-URL: Changelog, https://deezer-python.readthedocs.io/en/latest/changelog.html
Project-URL: documentation, https://deezer-python.readthedocs.io
Project-URL: Mastodon, https://fosstodon.org/@browniebroke
Project-URL: repository, https://github.com/browniebroke/deezer-python
Project-URL: Twitter, https://twitter.com/_BrunoAlla
Keywords: client,deezer,requests,sdk
Classifier: Development Status :: 5 - Production/Stable
Classifier: Intended Audience :: Developers
Classifier: Natural Language :: English
Classifier: Operating System :: OS Independent
Classifier: Programming Language :: Python :: 3 :: Only
Classifier: Programming Language :: Python :: 3.10
Classifier: Programming Language :: Python :: 3.11
Classifier: Programming Language :: Python :: 3.12
Classifier: Programming Language :: Python :: 3.13
Classifier: Programming Language :: Python :: 3.14
Classifier: Topic :: Software Development :: Libraries
Requires-Python: >=3.10
License-File: LICENSE.txt
Requires-Dist: httpx>=0.23
Dynamic: license-file
